{
  "stations": {
    "1": [
      "Бульвар Рокоссовского Улица Подбельского (до 2014)",
      "Черкизовская",
      "Преображенская площадь",
      "Сокольники",
      "Красносельская",
      "Комсомольская",
      "Красные Ворота Лермонтовская (с 1962 до 1986)",
      "Чистые пруды Кировская (до 1990)",
      "Лубянка Дзержинская (до 1990)",
      "Охотный Ряд Имени Л. М. Кагановича (с 1955 до 1957) Проспект Маркса (с 1961 до 1990)",
      "Библиотека имени Ленина",
      "Кропоткинская Дворец Советов (до 1957)",
      "Парк культуры Парк Культуры имени Горького (до 1960-х)",
      "Фрунзенская",
      "Спортивная",
      "Воробьёвы горы Ленинские горы (до 1999)",
      "Университет",
      "Проспект Вернадского",
      "Юго-Западная",
      "Тропарёво",
      "Румянцево",
      "Саларьево",
      "Филатов луг",
      "Прокшино",
      "Ольховая",
      "Коммунарка"
    ],
    "2": [
      "Ховрино",
      "Беломорская",
      "Речной вокзал",
      "Водный стадион",
      "Войковская",
      "Сокол",
      "Аэропорт",
      "Динамо",
      "Белорусская",
      "Маяковская",
      "Тверская Горьковская (до 1990)",
      "Театральная Площадь Свердлова (до 1990)",
      "Новокузнецкая",
      "Павелецкая",
      "Автозаводская Завод имени Сталина (до 1956)",
      "Технопарк",
      "Коломенская",
      "Каширская",
      "Кантемировская",
      "Царицыно Ленино (до 1990)",
      "Орехово",
      "Домодедовская",
      "Красногвардейская",
      "Алма-Атинская"
    ],
    "3": [
      "Пятницкое шоссе",
      "Митино",
      "Волоколамская",
      "Мякинино",
      "Строгино",
      "Крылатское",
      "Молодёжная",
      "Кунцевская",
      "Славянский бульвар",
      "Парк Победы",
      "Киевская",
      "Смоленская",
      "Арбатская",
      "Площадь Революции",
      "Курская",
      "Бауманская",
      "Электрозаводская",
      "Семёновская Сталинская (до 1961)",
      "Партизанская Измайловский парк культуры и отдыха имени Сталина (до 1947) Измайловская (до 1963) Измайловский парк (до 2005)",
      "Измайловская Измайловский парк (до 1963)",
      "Первомайская",
      "Щёлковская"
    ],
    "4": [
      "Кунцевская",
      "Пионерская",
      "Филёвский парк",
      "Багратионовская",
      "Фили",
      "Кутузовская",
      "Студенческая",
      "Международная",
      "Выставочная Деловой центр (до 2008)",
      "Киевская",
      "Смоленская",
      "Арбатская",
      "Александровский сад Улица Коминтерна (до 1946) Калининская (до 1990)"
    ],
    "5": [
      "Парк культуры Парк Культуры имени Горького (до 1960-х)",
      "Октябрьская Калужская (до 1961)",
      "Добрынинская Серпуховская (до 1961)",
      "Павелецкая",
      "Таганская",
      "Курская",
      "Комсомольская",
      "Проспект Мира Ботанический сад (до 1966)",
      "Новослободская",
      "Белорусская",
      "Краснопресненская",
      "Киевская"
    ],
    "6": [
      "Медведково",
      "Бабушкинская",
      "Свиблово",
      "Ботанический сад",
      "ВДНХ ВСХВ (до 1959)",
      "Алексеевская Мир (до 1966) Щербаковская (до 1990)",
      "Рижская",
      "Проспект Мира Ботанический сад (до 1966)",
      "Сухаревская Колхозная (до 1990)",
      "Тургеневская",
      "Китай-город Площадь Ногина (до 1990)",
      "Третьяковская Новокузнецкая (до 1983)",
      "Октябрьская",
      "Шаболовская",
      "Ленинский проспект",
      "Академическая",
      "Профсоюзная",
      "Новые Черёмушки",
      "Калужская",
      "Беляево",
      "Коньково",
      "Тёплый Стан",
      "Ясенево",
      "Новоясеневская Битцевский парк (до 2008)"
    ],
    "7": [
      "Планерная",
      "Сходненская",
      "Тушинская",
      "Спартак",
      "Щукинская",
      "Октябрьское Поле",
      "Полежаевская",
      "Беговая",
      "Улица 1905 года",
      "Баррикадная",
      "Пушкинская",
      "Кузнецкий Мост",
      "Китай-город Площадь Ногина (до 1990)",
      "Таганская",
      "Пролетарская",
      "Волгоградский проспект",
      "Текстильщики",
      "Кузьминки",
      "Рязанский проспект",
      "Выхино Ждановская (до 1989)",
      "Лермонтовский проспект",
      "Жулебино",
      "Котельники"
    ],
    "8": [
      "Третьяковская",
      "Марксистская",
      "Площадь Ильича",
      "Авиамоторная",
      "Шоссе Энтузиастов",
      "Перово",
      "Новогиреево",
      "Новокосино"
    ],
    "8А": [
      "Рассказовка",
      "Новопеределкино",
      "Боровское шоссе",
      "Солнцево",
      "Говорово",
      "Озёрная",
      "Мичуринский проспект",
      "Раменки",
      "Ломоносовский проспект",
      "Минская",
      "Парк Победы",
      "Деловой центр (закрыта с 24 февраля 2018)"
    ],
    "9": [
      "Алтуфьево",
      "Бибирево",
      "Отрадное",
      "Владыкино",
      "Петровско-Разумовская",
      "Тимирязевская",
      "Дмитровская",
      "Савёловская",
      "Менделеевская",
      "Цветной бульвар",
      "Чеховская",
      "Боровицкая",
      "Полянка",
      "Серпуховская",
      "Тульская",
      "Нагатинская",
      "Нагорная",
      "Нахимовский проспект",
      "Севастопольская",
      "Чертановская",
      "Южная",
      "Пражская",
      "Улица Академика Янгеля",
      "Аннино",
      "Бульвар Дмитрия Донского"
    ],
    "10": [
      "Селигерская",
      "Верхние Лихоборы",
      "Окружная",
      "Петровско-Разумовская",
      "Фонвизинская",
      "Бутырская",
      "Марьина Роща",
      "Достоевская",
      "Трубная",
      "Сретенский бульвар",
      "Чкаловская",
      "Римская",
      "Крестьянская застава",
      "Дубровка",
      "Кожуховская",
      "Печатники",
      "Волжская",
      "Люблино",
      "Братиславская",
      "Марьино",
      "Борисово",
      "Шипиловская",
      "Зябликово"
    ],
    "11": [
      "Деловой центр",
      "Шелепиха",
      "Хорошёвская",
      "ЦСКА",
      "Петровский парк",
      "Савёловская"
    ],
    "11А": [
      "Каширская (закрыта с 26 октября 2019)",
      "Варшавская (закрыта с 26 октября 2019)",
      "Каховская (закрыта с 30 марта 2019)"
    ],
    "12": [
      "Битцевский парк",
      "Лесопарковая",
      "Улица Старокачаловская",
      "Улица Скобелевская",
      "Бульвар Адмирала Ушакова",
      "Улица Горчакова",
      "Бунинская аллея"
    ],
    "15": [
      "Косино",
      "Улица Дмитриевского",
      "Лухмановская",
      "Некрасовка"
    ]
  },
  "lines": [
    {
      "number": "1",
      "name": "Сокольническая"
    },
    {
      "number": "2",
      "name": "Замоскворецкая"
    },
    {
      "number": "3",
      "name": "Арбатско-Покровская"
    },
    {
      "number": "4",
      "name": "Филёвская"
    },
    {
      "number": "5",
      "name": "Кольцевая"
    },
    {
      "number": "6",
      "name": "Калужско-Рижская"
    },
    {
      "number": "7",
      "name": "Таганско-Краснопресненская"
    },
    {
      "number": "8",
      "name": "Калининская"
    },
    {
      "number": "8А",
      "name": "Солнцевская"
    },
    {
      "number": "9",
      "name": "Серпуховско-Тимирязевская"
    },
    {
      "number": "10",
      "name": "Люблинско-Дмитровская"
    },
    {
      "number": "11",
      "name": "Большая"
    },
    {
      "number": "11А",
      "name": "Каховская"
    },
    {
      "number": "12",
      "name": "Бутовская"
    },
    {
      "number": "15",
      "name": "Некрасовская"
    }
  ],
  "connections": [
    [
      {
        "line": "1",
        "station": "Библиотека имени Ленина"
      },
      {
        "line": "3",
        "station": "Арбатская"
      },
      {
        "line": "9",
        "station": "Боровицкая"
      }
    ],
    [
      {
        "line": "1",
        "station": "Комсомольская"
      },
      {
        "line": "5",
        "station": "Комсомольская"
      }
    ],
    [
      {
        "line": "1",
        "station": "Лубянка"
      },
      {
        "line": "7",
        "station": "Кузнецкий Мост"
      }
    ],
    [
      {
        "line": "1",
        "station": "Охотный Ряд"
      }
    ],
    [
      {
        "line": "1",
        "station": "Парк культуры"
      }
    ],
    [
      {
        "line": "1",
        "station": "Чистые пруды"
      },
      {
        "line": "6",
        "station": "Тургеневская"
      },
      {
        "line": "10",
        "station": "Сретенский бульвар"
      }
    ],
    [
      {
        "line": "2",
        "station": "Белорусская"
      },
      {
        "line": "5",
        "station": "Белорусская"
      }
    ],
    [
      {
        "line": "2",
        "station": "Динамо"
      },
      {
        "line": "11",
        "station": "Петровский парк"
      }
    ],
    [
      {
        "line": "2",
        "station": "Каширская"
      }
    ],
    [
      {
        "line": "2",
        "station": "Красногвардейская"
      },
      {
        "line": "10",
        "station": "Зябликово"
      }
    ],
    [
      {
        "line": "2",
        "station": "Новокузнецкая"
      },
      {
        "line": "8",
        "station": "Третьяковская"
      }
    ],
    [
      {
        "line": "2",
        "station": "Павелецкая"
      },
      {
        "line": "5",
        "station": "Павелецкая"
      }
    ],
    [
      {
        "line": "2",
        "station": "Тверская"
      },
      {
        "line": "7",
        "station": "Пушкинская"
      },
      {
        "line": "9",
        "station": "Чеховская"
      }
    ],
    [
      {
        "line": "2",
        "station": "Театральная"
      },
      {
        "line": "3",
        "station": "Площадь Революции"
      }
    ],
    [
      {
        "line": "3",
        "station": "Арбатская"
      },
      {
        "line": "1",
        "station": "Библиотека имени Ленина"
      },
      {
        "line": "9",
        "station": "Боровицкая"
      }
    ],
    [
      {
        "line": "3",
        "station": "Киевская"
      },
      {
        "line": "4",
        "station": "Киевская"
      },
      {
        "line": "5",
        "station": "Киевская"
      }
    ],
    [
      {
        "line": "3",
        "station": "Кунцевская"
      },
      {
        "line": "4",
        "station": "Кунцевская"
      }
    ],
    [
      {
        "line": "3",
        "station": "Курская"
      },
      {
        "line": "5",
        "station": "Курская"
      },
      {
        "line": "10",
        "station": "Чкаловская"
      }
    ],
    [
      {
        "line": "3",
        "station": "Парк Победы"
      },
      {
        "line": "8А",
        "station": "Парк Победы"
      }
    ],
    [
      {
        "line": "3",
        "station": "Площадь Революции"
      }
    ],
    [
      {
        "line": "4",
        "station": "Александровский сад"
      },
      {
        "line": "1",
        "station": "Библиотека имени Ленина"
      },
      {
        "line": "3",
        "station": "Арбатская"
      }
    ],
    [
      {
        "line": "4",
        "station": "Выставочная"
      },
      {
        "line": "11",
        "station": "Деловой центр"
      }
    ],
    [
      {
        "line": "4",
        "station": "Киевская"
      },
      {
        "line": "3",
        "station": "Киевская"
      },
      {
        "line": "5",
        "station": "Киевская"
      }
    ],
    [
      {
        "line": "4",
        "station": "Кунцевская"
      },
      {
        "line": "3",
        "station": "Кунцевская"
      }
    ],
    [
      {
        "line": "5",
        "station": "Белорусская"
      },
      {
        "line": "2",
        "station": "Белорусская"
      }
    ],
    [
      {
        "line": "5",
        "station": "Добрынинская"
      },
      {
        "line": "9",
        "station": "Серпуховская"
      }
    ],
    [
      {
        "line": "5",
        "station": "Киевская"
      },
      {
        "line": "3",
        "station": "Киевская"
      },
      {
        "line": "4",
        "station": "Киевская"
      }
    ],
    [
      {
        "line": "5",
        "station": "Комсомольская"
      },
      {
        "line": "1",
        "station": "Комсомольская"
      }
    ],
    [
      {
        "line": "5",
        "station": "Краснопресненская"
      },
      {
        "line": "7",
        "station": "Баррикадная"
      }
    ],
    [
      {
        "line": "5",
        "station": "Курская"
      },
      {
        "line": "3",
        "station": "Курская"
      },
      {
        "line": "10",
        "station": "Чкаловская"
      }
    ],
    [
      {
        "line": "5",
        "station": "Новослободская"
      },
      {
        "line": "9",
        "station": "Менделеевская"
      }
    ],
    [
      {
        "line": "5",
        "station": "Октябрьская"
      },
      {
        "line": "6",
        "station": "Октябрьская"
      }
    ],
    [
      {
        "line": "5",
        "station": "Павелецкая"
      },
      {
        "line": "2",
        "station": "Павелецкая"
      }
    ],
    [
      {
        "line": "5",
        "station": "Парк культуры"
      }
    ],
    [
      {
        "line": "5",
        "station": "Проспект Мира"
      }
    ],
    [
      {
        "line": "5",
        "station": "Таганская"
      },
      {
        "line": "7",
        "station": "Таганская"
      },
      {
        "line": "8",
        "station": "Марксистская"
      }
    ],
    [
      {
        "line": "6",
        "station": "Китай-город"
      }
    ],
    [
      {
        "line": "6",
        "station": "Новоясеневская"
      },
      {
        "line": "12",
        "station": "Битцевский парк"
      }
    ],
    [
      {
        "line": "6",
        "station": "Октябрьская"
      }
    ],
    [
      {
        "line": "6",
        "station": "Проспект Мира"
      }
    ],
    [
      {
        "line": "6",
        "station": "Третьяковская"
      },
      {
        "line": "2",
        "station": "Новокузнецкая"
      },
      {
        "line": "8",
        "station": "Третьяковская"
      }
    ],
    [
      {
        "line": "6",
        "station": "Тургеневская"
      },
      {
        "line": "10",
        "station": "Сретенский бульвар"
      }
    ],
    [
      {
        "line": "7",
        "station": "Баррикадная"
      },
      {
        "line": "5",
        "station": "Краснопресненская"
      }
    ],
    [
      {
        "line": "7",
        "station": "Китай-город"
      }
    ],
    [
      {
        "line": "7",
        "station": "Кузнецкий Мост"
      }
    ],
    [
      {
        "line": "7",
        "station": "Лермонтовский проспект"
      },
      {
        "line": "15",
        "station": "Косино"
      }
    ],
    [
      {
        "line": "7",
        "station": "Пролетарская"
      },
      {
        "line": "10",
        "station": "Крестьянская застава"
      }
    ],
    [
      {
        "line": "7",
        "station": "Пушкинская"
      },
      {
        "line": "9",
        "station": "Чеховская"
      }
    ],
    [
      {
        "line": "7",
        "station": "Таганская"
      },
      {
        "line": "5",
        "station": "Таганская"
      },
      {
        "line": "8",
        "station": "Марксистская"
      }
    ],
    [
      {
        "line": "8",
        "station": "Марксистская"
      },
      {
        "line": "5",
        "station": "Таганская"
      },
      {
        "line": "7",
        "station": "Таганская"
      }
    ],
    [
      {
        "line": "8",
        "station": "Площадь Ильича"
      },
      {
        "line": "10",
        "station": "Римская"
      }
    ],
    [
      {
        "line": "8",
        "station": "Третьяковская"
      },
      {
        "line": "2",
        "station": "Новокузнецкая"
      }
    ],
    [
      {
        "line": "8А",
        "station": "Деловой центр"
      },
      {
        "line": "11",
        "station": "Деловой центр"
      }
    ],
    [
      {
        "line": "8А",
        "station": "Парк Победы"
      },
      {
        "line": "3",
        "station": "Парк Победы"
      }
    ],
    [
      {
        "line": "8А",
        "station": "Петровский парк"
      },
      {
        "line": "2",
        "station": "Динамо"
      }
    ],
    [
      {
        "line": "8А",
        "station": "Савёловская"
      },
      {
        "line": "9",
        "station": "Савёловская"
      }
    ],
    [
      {
        "line": "9",
        "station": "Боровицкая"
      },
      {
        "line": "1",
        "station": "Библиотека имени Ленина"
      },
      {
        "line": "3",
        "station": "Арбатская"
      }
    ],
    [
      {
        "line": "9",
        "station": "Бульвар Дмитрия Донского"
      },
      {
        "line": "12",
        "station": "Улица Старокачаловская"
      }
    ],
    [
      {
        "line": "9",
        "station": "Менделеевская"
      },
      {
        "line": "5",
        "station": "Новослободская"
      }
    ],
    [
      {
        "line": "9",
        "station": "Петровско-Разумовская"
      },
      {
        "line": "10",
        "station": "Петровско-Разумовская"
      }
    ],
    [
      {
        "line": "9",
        "station": "Севастопольская"
      }
    ],
    [
      {
        "line": "9",
        "station": "Серпуховская"
      }
    ],
    [
      {
        "line": "9",
        "station": "Цветной бульвар"
      },
      {
        "line": "10",
        "station": "Трубная"
      }
    ],
    [
      {
        "line": "9",
        "station": "Чеховская"
      },
      {
        "line": "7",
        "station": "Пушкинская"
      }
    ],
    [
      {
        "line": "10",
        "station": "Зябликово"
      },
      {
        "line": "2",
        "station": "Красногвардейская"
      }
    ],
    [
      {
        "line": "10",
        "station": "Крестьянская застава"
      },
      {
        "line": "7",
        "station": "Пролетарская"
      }
    ],
    [
      {
        "line": "10",
        "station": "Петровско-Разумовская"
      },
      {
        "line": "9",
        "station": "Петровско-Разумовская"
      }
    ],
    [
      {
        "line": "10",
        "station": "Римская"
      },
      {
        "line": "8",
        "station": "Площадь Ильича"
      }
    ],
    [
      {
        "line": "10",
        "station": "Сретенский бульвар"
      },
      {
        "line": "6",
        "station": "Тургеневская"
      }
    ],
    [
      {
        "line": "10",
        "station": "Трубная"
      },
      {
        "line": "9",
        "station": "Цветной бульвар"
      }
    ],
    [
      {
        "line": "10",
        "station": "Чкаловская"
      },
      {
        "line": "3",
        "station": "Курская"
      },
      {
        "line": "5",
        "station": "Курская"
      }
    ],
    [
      {
        "line": "11",
        "station": "Деловой центр"
      }
    ],
    [
      {
        "line": "11",
        "station": "Петровский парк"
      },
      {
        "line": "2",
        "station": "Динамо"
      }
    ],
    [
      {
        "line": "11",
        "station": "Савёловская"
      },
      {
        "line": "9",
        "station": "Савёловская"
      }
    ],
    [
      {
        "line": "11А",
        "station": "Каховская"
      },
      {
        "line": "9",
        "station": "Севастопольская"
      }
    ],
    [
      {
        "line": "11А",
        "station": "Каширская"
      },
      {
        "line": "2",
        "station": "Каширская"
      }
    ],
    [
      {
        "line": "12",
        "station": "Битцевский парк"
      }
    ],
    [
      {
        "line": "12",
        "station": "Улица Старокачаловская"
      },
      {
        "line": "9",
        "station": "Бульвар Дмитрия Донского"
      }
    ],
    [
      {
        "line": "13",
        "station": "Выставочный центр"
      }
    ],
    [
      {
        "line": "13",
        "station": "Тимирязевская"
      },
      {
        "line": "9",
        "station": "Тимирязевская"
      }
    ],
    [
      {
        "line": "13",
        "station": "Улица Милашенкова"
      },
      {
        "line": "10",
        "station": "Фонвизинская"
      }
    ],
    [
      {
        "line": "14",
        "station": "Автозаводская"
      }
    ],
    [
      {
        "line": "14",
        "station": "Балтийская"
      },
      {
        "line": "2",
        "station": "Войковская"
      }
    ],
    [
      {
        "line": "14",
        "station": "Ботанический сад"
      },
      {
        "line": "6",
        "station": "Ботанический сад"
      }
    ],
    [
      {
        "line": "14",
        "station": "Бульвар Рокоссовского"
      }
    ],
    [
      {
        "line": "14",
        "station": "Верхние Котлы"
      },
      {
        "line": "9",
        "station": "Нагатинская"
      }
    ],
    [
      {
        "line": "14",
        "station": "Владыкино"
      },
      {
        "line": "9",
        "station": "Владыкино"
      }
    ],
    [
      {
        "line": "14",
        "station": "Деловой центр"
      },
      {
        "line": "4",
        "station": "Международная"
      }
    ],
    [
      {
        "line": "14",
        "station": "Дубровка"
      },
      {
        "line": "10",
        "station": "Дубровка"
      }
    ],
    [
      {
        "line": "14",
        "station": "Измайлово"
      }
    ],
    [
      {
        "line": "14",
        "station": "Кутузовская"
      },
      {
        "line": "4",
        "station": "Кутузовская"
      }
    ],
    [
      {
        "line": "14",
        "station": "Локомотив"
      },
      {
        "line": "1",
        "station": "Черкизовская"
      }
    ],
    [
      {
        "line": "14",
        "station": "Лужники"
      },
      {
        "line": "1",
        "station": "Спортивная"
      }
    ],
    [
      {
        "line": "14",
        "station": "Окружная"
      },
      {
        "line": "10",
        "station": "Окружная"
      }
    ],
    [
      {
        "line": "14",
        "station": "Панфиловская"
      },
      {
        "line": "7",
        "station": "Октябрьское Поле"
      }
    ],
    [
      {
        "line": "14",
        "station": "Площадь Гагарина"
      },
      {
        "line": "6",
        "station": "Ленинский проспект"
      }
    ],
    [
      {
        "line": "14",
        "station": "Угрешская"
      },
      {
        "line": "7",
        "station": "Волгоградский проспект"
      }
    ],
    [
      {
        "line": "14",
        "station": "Хорошёво"
      },
      {
        "line": "7",
        "station": "Полежаевская"
      },
      {
        "line": "11",
        "station": "Хорошёвская"
      }
    ],
    [
      {
        "line": "14",
        "station": "Шелепиха"
      },
      {
        "line": "11",
        "station": "Шелепиха"
      }
    ],
    [
      {
        "line": "14",
        "station": "Шоссе Энтузиастов"
      },
      {
        "line": "8",
        "station": "Шоссе Энтузиастов"
      }
    ],
    [
      {
        "line": "15",
        "station": "Косино"
      },
      {
        "line": "7",
        "station": "Лермонтовский проспект"
      }
    ]
  ]
}